license_expression/__init__.py
license_expression/_pyahocorasick.ABOUT
license_expression/_pyahocorasick.py
license_expression/data/cc-by-4.0.LICENSE
license_expression/data/license_key_index.json.ABOUT
license_expression/data/scancode-licensedb-index.json
license_expression-30.4.0.dist-info/AUTHORS.rst
license_expression-30.4.0.dist-info/CHANGELOG.rst
license_expression-30.4.0.dist-info/CODE_OF_CONDUCT.rst
license_expression-30.4.0.dist-info/METADATA
license_expression-30.4.0.dist-info/NOTICE
license_expression-30.4.0.dist-info/WHEEL
license_expression-30.4.0.dist-info/apache-2.0.LICENSE
license_expression-30.4.0.dist-info/top_level.txt
license_expression-30.4.0.dist-info/RECORD
